{
  "id": "formfor-pick-invalid-field",
  "description": "§41.14.5 — pick=[\"X\", ...] on <formFor for=T> naming a field not present on struct T fires E-FORMFOR-PICK-INVALID-FIELD. Signup has { name, email, agree }; pick=[\"nope\"] names a non-field.",
  "language-version": "1.0",
  "spec": "§41.14.5",
  "rationale": "§41.14.5 E-FORMFOR-PICK-INVALID-FIELD: the pick=[...] attribute SHALL name only declared struct fields; an unknown name is rejected. Fix: correct or remove the invalid field name from the pick array.",
  "expect": {
    "codes": ["E-FORMFOR-PICK-INVALID-FIELD"],
    "notCodes": ["E-FORMFOR-OMIT-INVALID-FIELD", "E-FORMFOR-PICK-OMIT-CONFLICT"]
  }
}
